CHANGES.txt
COPYRIGHT.txt
LICENSE.txt
MANIFEST.in
README.txt
setup.py
src/z3c/__init__.py
src/z3c.xmlhttp.egg-info/PKG-INFO
src/z3c.xmlhttp.egg-info/SOURCES.txt
src/z3c.xmlhttp.egg-info/dependency_links.txt
src/z3c.xmlhttp.egg-info/namespace_packages.txt
src/z3c.xmlhttp.egg-info/not-zip-safe
src/z3c.xmlhttp.egg-info/requires.txt
src/z3c.xmlhttp.egg-info/top_level.txt
src/z3c/xmlhttp/__init__.py
src/z3c/xmlhttp/browser.py
src/z3c/xmlhttp/browser.zcml
src/z3c/xmlhttp/configure.zcml
src/z3c/xmlhttp/layer.py
src/z3c/xmlhttp/js/z3c.xmlhttp-0.5.0.js