Metadata-Version: 1.0
Name: z3c.xmlhttp
Version: 0.5.1
Summary: XMLHttpRequest (XHR) javascript
Home-page: http://pypi.python.org/pypi/z3c.xmlhttp
Author: Roger Ineichen and the Zope Community
Author-email: zope3-dev@zope.org
License: ZPL 2.1
Keywords: zope3 z3c xhr xmlhttp XMLHttp request proxy javascript js ajax
Platform: UNKNOWN
Classifier: Development Status :: 4 - Beta
Classifier: Environment :: Web Environment
Classifier: Intended Audience :: Developers
Classifier: License :: OSI Approved :: Zope Public License
Classifier: Programming Language :: Python
Classifier: Natural Language :: English
Classifier: Operating System :: OS Independent
Classifier: Topic :: Internet :: WWW/HTTP
Classifier: Framework :: Zope3
